netrise_turbine_sdk/__init__.py
netrise_turbine_sdk/client.py
netrise_turbine_sdk_graphql/__init__.py
netrise_turbine_sdk_graphql/base_client.py
netrise_turbine_sdk_graphql/base_model.py
netrise_turbine_sdk_graphql/client.py
netrise_turbine_sdk_graphql/custom_scalars.py
netrise_turbine_sdk_graphql/enums.py
netrise_turbine_sdk_graphql/exceptions.py
netrise_turbine_sdk_graphql/input_types.py
netrise_turbine_sdk_graphql/mutation_add_asset_groups_to_assets.py
netrise_turbine_sdk_graphql/mutation_add_assets_to_asset_group.py
netrise_turbine_sdk_graphql/mutation_asset_add_dependency.py
netrise_turbine_sdk_graphql/mutation_asset_modify_dependency.py
netrise_turbine_sdk_graphql/mutation_asset_remove_dependencies.py
netrise_turbine_sdk_graphql/mutation_asset_submit.py
netrise_turbine_sdk_graphql/mutation_asset_update.py
netrise_turbine_sdk_graphql/mutation_create_asset_group.py
netrise_turbine_sdk_graphql/mutation_delete_asset_group.py
netrise_turbine_sdk_graphql/mutation_remediate_all_asset_vulnerabilities.py
netrise_turbine_sdk_graphql/mutation_remediate_asset_vulnerabilities.py
netrise_turbine_sdk_graphql/mutation_remediate_asset_vulnerability.py
netrise_turbine_sdk_graphql/mutation_remediate_license_issues.py
netrise_turbine_sdk_graphql/mutation_remove_all_asset_groups_from_assets.py
netrise_turbine_sdk_graphql/mutation_remove_assets_from_asset_group.py
netrise_turbine_sdk_graphql/mutation_set_asset_groups_to_asset.py
netrise_turbine_sdk_graphql/mutation_set_assets_to_asset_group.py
netrise_turbine_sdk_graphql/mutation_update_asset_group.py
netrise_turbine_sdk_graphql/mutation_update_org_level_settings.py
netrise_turbine_sdk_graphql/mutation_user_action.py
netrise_turbine_sdk_graphql/mutation_user_delete.py
netrise_turbine_sdk_graphql/mutation_user_invite.py
netrise_turbine_sdk_graphql/mutation_user_remove.py
netrise_turbine_sdk_graphql/mutation_user_reset_password.py
netrise_turbine_sdk_graphql/mutation_user_set_user_role.py
netrise_turbine_sdk-0.1.6.dist-info/METADATA
netrise_turbine_sdk-0.1.6.dist-info/WHEEL
netrise_turbine_sdk-0.1.6.dist-info/RECORD
