Metadata-Version: 2.4
Name: netrise-turbine-sdk
Version: 0.1.6
Summary: Turbine GraphQL Python SDK (generated via ariadne-codegen)
Author: NetRise
Author-email: anthony.feddersen@netrise.io
Requires-Python: >=3.12,<4.0
Classifier: Programming Language :: Python :: 3
Classifier: Programming Language :: Python :: 3.12
Classifier: Programming Language :: Python :: 3.13
Classifier: Programming Language :: Python :: 3.14
Requires-Dist: httpx (>=0.27.0,<1.0.0)
Requires-Dist: pydantic (>=2.0.0,<3.0.0)
Requires-Dist: python-dotenv (>=1.0.0,<2.0.0)
